database_automation/__init__.py
database_automation/mongo_crud.py
sivasakthi03_mongo_db_automation-0.0.3.dist-info/METADATA
sivasakthi03_mongo_db_automation-0.0.3.dist-info/WHEEL
sivasakthi03_mongo_db_automation-0.0.3.dist-info/top_level.txt
sivasakthi03_mongo_db_automation-0.0.3.dist-info/RECORD
